{
	"name": "CarsTable",
	"properties": {
		"linkedServiceName": {
			"referenceName": "AzureSqlDatabase1",
			"type": "LinkedServiceReference"
		},
		"annotations": [],
		"type": "AzureSqlTable",
		"schema": [
			{
				"name": "Car",
				"type": "varchar"
			},
			{
				"name": "Origin",
				"type": "varchar"
			},
			{
				"name": "Motor",
				"type": "decimal",
				"precision": 18,
				"scale": 3
			}
		],
		"typeProperties": {
			"schema": "dbo",
			"table": "Cars"
		}
	},
	"type": "Microsoft.DataFactory/factories/datasets"
}